scanno/__init__.py
scanno/scanno.py
scanno-0.0.2.dist-info/METADATA
scanno-0.0.2.dist-info/WHEEL
scanno-0.0.2.dist-info/top_level.txt
scanno-0.0.2.dist-info/RECORD
