Metadata-Version: 2.1
Name: scanno
Version: 0.0.2
Summary: scRNASeq analysis
Home-page: https://github.com/Hoa-Lab/scanno
Author: Shoujun Gu
Author-email: shoujun.gu@gmail.com
License: UNKNOWN
Project-URL: Bug Tracker, https://github.com/Hoa-Lab/scanno/issues
Platform: UNKNOWN
Classifier: Programming Language :: Python :: 3
Classifier: License :: OSI Approved :: MIT License
Classifier: Operating System :: OS Independent
Requires-Python: >=3.6
